{
  "WorkItem": {
    "AffectedComponent": {
      "Name": "",
      "DisplayName": ""
    },
    "ClosedComment": "added in changeset 101571",
    "ClosedDate": "2013-07-07T12:09:08.243-07:00",
    "CommentCount": 0,
    "Custom": "",
    "Description": "Add a Style for the Date Picker Control.",
    "LastUpdatedDate": "2013-07-07T12:09:08.243-07:00",
    "PlannedForRelease": "",
    "ReleaseVisibleToPublic": false,
    "Priority": {
      "Name": "Unassigned",
      "Severity": 0,
      "Id": 0
    },
    "ProjectName": "mui",
    "ReportedDate": "2013-03-05T09:02:33.88-08:00",
    "Status": {
      "Name": "Closed",
      "Id": 4
    },
    "ReasonClosed": {
      "Name": "Unassigned"
    },
    "Summary": "Date Picker Control",
    "Type": {
      "Name": "Issue",
      "Id": 3
    },
    "VoteCount": 25,
    "Id": 19429
  },
  "FileAttachments": [],
  "Comments": []
}