[
  {
    "Id": "1127451",
    "ThreadId": "470700",
    "Html": "Hello guys,\r<br />\n<br />\nI'm trying to create a small m:ui app, and I need some controls from Telerik.\r<br />\nIs there any way to achieve this, using the latest version of m:ui (1.0.5)?\r<br />\n<br />\nThere is previous discussion thread related to this. for version 1.0.2, but I was not able yet to make that work. Anyway, I would like to use the latest release.\r<br />\n<br />\nAny kind of help will be appreciated!\r<br />\nCheers!<br />\n",
    "PostedDate": "2013-11-21T02:23:57.427-08:00",
    "UserRole": null,
    "MarkedAsAnswerDate": null
  },
  {
    "Id": "1127662",
    "ThreadId": "470700",
    "Html": "All I had to do was install Telerik on my computer and include the references I needed in my project\r<br />\n<br />\nI am using a radgridview and some buttons so far.\r<br />\n<br />\nCan you show me what you treid to do so far?<br />\n",
    "PostedDate": "2013-11-21T11:13:46.98-08:00",
    "UserRole": null,
    "MarkedAsAnswerDate": null
  }
]